{
  "city": "Teays Valley",
  "slug": "teays-valley",
  "state": "West Virginia",
  "stateCode": "WV",
  "county": "Putnam County",
  "lat": 38.4501,
  "lng": -81.9293,
  "fetchedAt": "2026-02-11T17:08:27.797Z",
  "census": {
    "population": 57347,
    "medianAge": 42.2,
    "medianHouseholdIncome": 75725,
    "medianHomeValue": 202300,
    "medianRent": 1007,
    "povertyRate": 10.9,
    "unemploymentRate": 3.7,
    "bachelorDegreeOrHigher": 29.5,
    "publicTransitPct": 0.1,
    "workFromHomePct": 7.8,
    "demographics": {
      "white": 95,
      "black": 0.9,
      "asian": 0.8,
      "hispanic": 1.3,
      "other": 2
    },
    "source": "Census Bureau ACS 5-Year Estimates (2022)"
  },
  "health": {
    "measures": {
      "LPA": {
        "label": "Physical Inactivity",
        "value": 28.6,
        "unit": "%",
        "year": "2023"
      },
      "PHLTH": {
        "label": "Frequent Physical Distress",
        "value": 15.3,
        "unit": "%",
        "year": "2023"
      },
      "CHD": {
        "label": "Coronary Heart Disease",
        "value": 7.5,
        "unit": "%",
        "year": "2023"
      },
      "SLEEP": {
        "label": "Short Sleep Duration",
        "value": 40.3,
        "unit": "%",
        "year": "2022"
      },
      "DENTAL": {
        "label": "Dental Visit",
        "value": 62.9,
        "unit": "%",
        "year": "2022"
      },
      "MHLTH": {
        "label": "Frequent Mental Distress",
        "value": 19.6,
        "unit": "%",
        "year": "2023"
      },
      "DIABETES": {
        "label": "Diabetes",
        "value": 14.1,
        "unit": "%",
        "year": "2023"
      },
      "OBESITY": {
        "label": "Obesity",
        "value": 38.3,
        "unit": "%",
        "year": "2023"
      },
      "BINGE": {
        "label": "Binge Drinking",
        "value": 14.5,
        "unit": "%",
        "year": "2023"
      },
      "ACCESS2": {
        "label": "Lack of Health Insurance",
        "value": 6.9,
        "unit": "%",
        "year": "2023"
      },
      "CASTHMA": {
        "label": "Current Asthma",
        "value": 11.7,
        "unit": "%",
        "year": "2023"
      },
      "STROKE": {
        "label": "Stroke",
        "value": 3.6,
        "unit": "%",
        "year": "2023"
      },
      "CHECKUP": {
        "label": "Annual Checkup",
        "value": 82.3,
        "unit": "%",
        "year": "2023"
      },
      "BPHIGH": {
        "label": "High Blood Pressure",
        "value": 43.7,
        "unit": "%",
        "year": "2023"
      },
      "CSMOKING": {
        "label": "Current Smoking",
        "value": 16.3,
        "unit": "%",
        "year": "2023"
      }
    },
    "totalPopulation": 56962,
    "source": "CDC PLACES (2023)"
  },
  "hospitals": null,
  "crime": {
    "year": 2022,
    "source": "state",
    "sourceLabel": "FBI Crime Data Explorer (UCR Summary)",
    "violentCrimeRate": 241.4,
    "propertyCrimeRate": 1321.6,
    "assaultRate": 223.1,
    "homicideRate": 5.9,
    "robberyRate": 12.4,
    "burglaryRate": 214,
    "larcenyRate": 1007,
    "motorVehicleTheftRate": 100.6
  },
  "history": {
    "years": [
      2013,
      2014,
      2015,
      2016,
      2017,
      2018,
      2019,
      2020,
      2021,
      2022,
      2023
    ],
    "population": [
      56033,
      56356,
      56596,
      56743,
      56644,
      56652,
      56610,
      56604,
      57385,
      57347,
      57250
    ],
    "medianIncome": [
      54854,
      55939,
      56774,
      56640,
      59113,
      59626,
      60097,
      63954,
      68740,
      75725,
      77871
    ],
    "povertyRate": [
      11.3,
      10.1,
      9.8,
      9.8,
      9.3,
      9.2,
      9.8,
      10.8,
      10.5,
      10.9,
      10.7
    ],
    "medianHomeValue": [
      142900,
      146800,
      148600,
      151800,
      157500,
      163800,
      167300,
      175700,
      176300,
      202300,
      214200
    ],
    "unemploymentRate": [
      4.9,
      4.3,
      3.7,
      3.1,
      3.4,
      3.2,
      3.7,
      3.7,
      3.6,
      3.7,
      3.2
    ]
  },
  "climate": {
    "station": "USC00469683",
    "stationName": "WINFIELD LOCKS HCN",
    "distanceMi": 5.4,
    "source": "NOAA Climate Normals 1991-2020",
    "monthly": {
      "jan": {
        "avgTemp": 33.8,
        "highTemp": 43.6,
        "lowTemp": 24,
        "precip": 2.7
      },
      "feb": {
        "avgTemp": 36.8,
        "highTemp": 47.5,
        "lowTemp": 26.1,
        "precip": 2.9
      },
      "mar": {
        "avgTemp": 44.3,
        "highTemp": 56.3,
        "lowTemp": 32.3,
        "precip": 3.7
      },
      "apr": {
        "avgTemp": 55.3,
        "highTemp": 69,
        "lowTemp": 41.6,
        "precip": 3.2
      },
      "may": {
        "avgTemp": 63.9,
        "highTemp": 76.3,
        "lowTemp": 51.4,
        "precip": 4.1
      },
      "jun": {
        "avgTemp": 72.1,
        "highTemp": 84,
        "lowTemp": 60.2,
        "precip": 3.6
      },
      "jul": {
        "avgTemp": 75.8,
        "highTemp": 87,
        "lowTemp": 64.6,
        "precip": 4.3
      },
      "aug": {
        "avgTemp": 74.9,
        "highTemp": 86.4,
        "lowTemp": 63.4,
        "precip": 3.7
      },
      "sep": {
        "avgTemp": 68.7,
        "highTemp": 80.7,
        "lowTemp": 56.7,
        "precip": 2.9
      },
      "oct": {
        "avgTemp": 57.1,
        "highTemp": 69.5,
        "lowTemp": 44.6,
        "precip": 2.7
      },
      "nov": {
        "avgTemp": 46,
        "highTemp": 57.7,
        "lowTemp": 34.3,
        "precip": 2.6
      },
      "dec": {
        "avgTemp": 38,
        "highTemp": 47.3,
        "lowTemp": 28.6,
        "precip": 3.1
      }
    },
    "annual": {
      "avgTemp": 55.6,
      "highTemp": 67.1,
      "lowTemp": 44,
      "totalPrecip": 39.5,
      "hotMonths": 3,
      "coldMonths": 3
    }
  }
}
