{
  "city": "Americus",
  "slug": "americus",
  "state": "Georgia",
  "stateCode": "GA",
  "county": "Sumter County",
  "lat": 32.0724,
  "lng": -84.2327,
  "fetchedAt": "2026-02-11T17:08:27.735Z",
  "census": {
    "population": 29378,
    "medianAge": 36.9,
    "medianHouseholdIncome": 38899,
    "medianHomeValue": 130000,
    "medianRent": 812,
    "povertyRate": 24.2,
    "unemploymentRate": 6.4,
    "bachelorDegreeOrHigher": 22.2,
    "publicTransitPct": 0,
    "workFromHomePct": 7.8,
    "demographics": {
      "white": 41.8,
      "black": 51.1,
      "asian": 1.3,
      "hispanic": 6.1,
      "other": -0.3
    },
    "source": "Census Bureau ACS 5-Year Estimates (2022)"
  },
  "health": {
    "measures": {
      "STROKE": {
        "label": "Stroke",
        "value": 4.8,
        "unit": "%",
        "year": "2023"
      },
      "CHECKUP": {
        "label": "Annual Checkup",
        "value": 80,
        "unit": "%",
        "year": "2023"
      },
      "BPHIGH": {
        "label": "High Blood Pressure",
        "value": 43.6,
        "unit": "%",
        "year": "2023"
      },
      "CSMOKING": {
        "label": "Current Smoking",
        "value": 16.4,
        "unit": "%",
        "year": "2023"
      },
      "MHLTH": {
        "label": "Frequent Mental Distress",
        "value": 19.1,
        "unit": "%",
        "year": "2023"
      },
      "ACCESS2": {
        "label": "Lack of Health Insurance",
        "value": 14.9,
        "unit": "%",
        "year": "2023"
      },
      "OBESITY": {
        "label": "Obesity",
        "value": 39.5,
        "unit": "%",
        "year": "2023"
      },
      "DIABETES": {
        "label": "Diabetes",
        "value": 16.7,
        "unit": "%",
        "year": "2023"
      },
      "LPA": {
        "label": "Physical Inactivity",
        "value": 32.9,
        "unit": "%",
        "year": "2023"
      },
      "BINGE": {
        "label": "Binge Drinking",
        "value": 12.5,
        "unit": "%",
        "year": "2023"
      },
      "CHD": {
        "label": "Coronary Heart Disease",
        "value": 7.7,
        "unit": "%",
        "year": "2023"
      },
      "DENTAL": {
        "label": "Dental Visit",
        "value": 52.2,
        "unit": "%",
        "year": "2022"
      },
      "SLEEP": {
        "label": "Short Sleep Duration",
        "value": 41.7,
        "unit": "%",
        "year": "2022"
      },
      "PHLTH": {
        "label": "Frequent Physical Distress",
        "value": 15.8,
        "unit": "%",
        "year": "2023"
      },
      "CASTHMA": {
        "label": "Current Asthma",
        "value": 11.3,
        "unit": "%",
        "year": "2023"
      }
    },
    "totalPopulation": 28890,
    "source": "CDC PLACES (2023)"
  },
  "hospitals": {
    "hospitals": [
      {
        "name": "PHOEBE SUMTER MEDICAL CENTER",
        "city": "AMERICUS",
        "rating": 1,
        "type": "Acute Care Hospitals",
        "emergency": true,
        "ownership": "Government - Hospital District or Authority"
      }
    ],
    "totalHospitals": 1,
    "ratedHospitals": 1,
    "averageRating": 1,
    "source": "CMS Hospital Compare (2024)"
  }
}