{
  "city": "Moberly",
  "slug": "moberly",
  "state": "Missouri",
  "stateCode": "MO",
  "county": "Randolph County",
  "lat": 39.4184,
  "lng": -92.4382,
  "fetchedAt": "2026-02-11T17:08:27.778Z",
  "census": {
    "population": 24652,
    "medianAge": 39.8,
    "medianHouseholdIncome": 51480,
    "medianHomeValue": 131200,
    "medianRent": 735,
    "povertyRate": 17.2,
    "unemploymentRate": 5.3,
    "bachelorDegreeOrHigher": 17.1,
    "publicTransitPct": 0.5,
    "workFromHomePct": 5.3,
    "demographics": {
      "white": 88.9,
      "black": 5,
      "asian": 0.4,
      "hispanic": 2.2,
      "other": 3.5
    },
    "source": "Census Bureau ACS 5-Year Estimates (2022)"
  },
  "health": {
    "measures": {
      "BPHIGH": {
        "label": "High Blood Pressure",
        "value": 37.8,
        "unit": "%",
        "year": "2023"
      },
      "CASTHMA": {
        "label": "Current Asthma",
        "value": 10.9,
        "unit": "%",
        "year": "2023"
      },
      "PHLTH": {
        "label": "Frequent Physical Distress",
        "value": 15.9,
        "unit": "%",
        "year": "2023"
      },
      "SLEEP": {
        "label": "Short Sleep Duration",
        "value": 39.1,
        "unit": "%",
        "year": "2022"
      },
      "CHECKUP": {
        "label": "Annual Checkup",
        "value": 77.3,
        "unit": "%",
        "year": "2023"
      },
      "CSMOKING": {
        "label": "Current Smoking",
        "value": 19.4,
        "unit": "%",
        "year": "2023"
      },
      "ACCESS2": {
        "label": "Lack of Health Insurance",
        "value": 9.8,
        "unit": "%",
        "year": "2023"
      },
      "BINGE": {
        "label": "Binge Drinking",
        "value": 15.7,
        "unit": "%",
        "year": "2023"
      },
      "OBESITY": {
        "label": "Obesity",
        "value": 37.7,
        "unit": "%",
        "year": "2023"
      },
      "DIABETES": {
        "label": "Diabetes",
        "value": 12.7,
        "unit": "%",
        "year": "2023"
      },
      "CHD": {
        "label": "Coronary Heart Disease",
        "value": 7.6,
        "unit": "%",
        "year": "2023"
      },
      "LPA": {
        "label": "Physical Inactivity",
        "value": 31.9,
        "unit": "%",
        "year": "2023"
      },
      "STROKE": {
        "label": "Stroke",
        "value": 4,
        "unit": "%",
        "year": "2023"
      },
      "MHLTH": {
        "label": "Frequent Mental Distress",
        "value": 18.8,
        "unit": "%",
        "year": "2023"
      },
      "DENTAL": {
        "label": "Dental Visit",
        "value": 55.9,
        "unit": "%",
        "year": "2022"
      }
    },
    "totalPopulation": 24109,
    "source": "CDC PLACES (2023)"
  },
  "hospitals": {
    "hospitals": [
      {
        "name": "MOBERLY REGIONAL MEDICAL CENTER",
        "city": "MOBERLY",
        "rating": 2,
        "type": "Acute Care Hospitals",
        "emergency": true,
        "ownership": "Proprietary"
      }
    ],
    "totalHospitals": 1,
    "ratedHospitals": 1,
    "averageRating": 2,
    "source": "CMS Hospital Compare (2024)"
  },
  "crime": {
    "year": 2022,
    "source": "state",
    "sourceLabel": "FBI Crime Data Explorer (UCR Summary)",
    "violentCrimeRate": 447.4,
    "propertyCrimeRate": 2401.1,
    "assaultRate": 380.4,
    "homicideRate": 10.5,
    "robberyRate": 56.5,
    "burglaryRate": 301.2,
    "larcenyRate": 1590,
    "motorVehicleTheftRate": 509.9
  },
  "history": {
    "years": [
      2013,
      2014,
      2015,
      2016,
      2017,
      2018,
      2019,
      2020,
      2021,
      2022,
      2023
    ],
    "population": [
      25253,
      25207,
      25135,
      25081,
      24987,
      24945,
      24878,
      24769,
      24880,
      24652,
      24524
    ],
    "medianIncome": [
      37203,
      39316,
      37832,
      40638,
      44754,
      46610,
      47740,
      50440,
      51403,
      51480,
      55310
    ],
    "povertyRate": [
      19.4,
      18.7,
      19.1,
      17.6,
      16.5,
      15.5,
      16.4,
      15.4,
      16.2,
      17.2,
      15.8
    ],
    "medianHomeValue": [
      84600,
      85500,
      85500,
      89300,
      93800,
      101700,
      105000,
      108600,
      120000,
      131200,
      141900
    ],
    "unemploymentRate": [
      8.8,
      8.7,
      8.9,
      7.5,
      6.1,
      5.7,
      5.4,
      4.4,
      4.7,
      5.3,
      4.4
    ]
  },
  "climate": {
    "station": "USC00235671",
    "stationName": "MOBERLY HCN",
    "distanceMi": 0.1,
    "source": "NOAA Climate Normals 1991-2020",
    "monthly": {
      "jan": {
        "avgTemp": 28,
        "highTemp": 37.1,
        "lowTemp": 18.9,
        "precip": 1.9
      },
      "feb": {
        "avgTemp": 32.5,
        "highTemp": 42.2,
        "lowTemp": 22.7,
        "precip": 2.1
      },
      "mar": {
        "avgTemp": 43.8,
        "highTemp": 53.9,
        "lowTemp": 33.6,
        "precip": 3.3
      },
      "apr": {
        "avgTemp": 54.4,
        "highTemp": 64.7,
        "lowTemp": 44.1,
        "precip": 4.6
      },
      "may": {
        "avgTemp": 64.5,
        "highTemp": 74.2,
        "lowTemp": 54.9,
        "precip": 5.1
      },
      "jun": {
        "avgTemp": 73.2,
        "highTemp": 82.8,
        "lowTemp": 63.7,
        "precip": 5.2
      },
      "jul": {
        "avgTemp": 77.3,
        "highTemp": 87,
        "lowTemp": 67.5,
        "precip": 4.5
      },
      "aug": {
        "avgTemp": 75.7,
        "highTemp": 85.6,
        "lowTemp": 65.7,
        "precip": 3.9
      },
      "sep": {
        "avgTemp": 67.8,
        "highTemp": 78.2,
        "lowTemp": 57.3,
        "precip": 4
      },
      "oct": {
        "avgTemp": 56.3,
        "highTemp": 66.8,
        "lowTemp": 45.9,
        "precip": 3.4
      },
      "nov": {
        "avgTemp": 43.5,
        "highTemp": 53.2,
        "lowTemp": 33.8,
        "precip": 2.7
      },
      "dec": {
        "avgTemp": 33.3,
        "highTemp": 42,
        "lowTemp": 24.7,
        "precip": 2.2
      }
    },
    "annual": {
      "avgTemp": 54.2,
      "highTemp": 64,
      "lowTemp": 44.4,
      "totalPrecip": 42.9,
      "hotMonths": 3,
      "coldMonths": 3
    }
  }
}
