{
  "city": "Hutchinson",
  "slug": "hutchinson-mn",
  "state": "Minnesota",
  "stateCode": "MN",
  "county": "McLeod County",
  "lat": 44.8877,
  "lng": -94.3697,
  "fetchedAt": "2026-02-11T17:08:27.779Z",
  "census": {
    "population": 36727,
    "medianAge": 41.3,
    "medianHouseholdIncome": 73296,
    "medianHomeValue": 214300,
    "medianRent": 831,
    "povertyRate": 7.1,
    "unemploymentRate": 3.2,
    "bachelorDegreeOrHigher": 18.9,
    "publicTransitPct": 0.5,
    "workFromHomePct": 6.9,
    "demographics": {
      "white": 92.2,
      "black": 0.6,
      "asian": 0.7,
      "hispanic": 6.9,
      "other": -0.4
    },
    "source": "Census Bureau ACS 5-Year Estimates (2022)"
  },
  "health": {
    "measures": {
      "CSMOKING": {
        "label": "Current Smoking",
        "value": 14.9,
        "unit": "%",
        "year": "2023"
      },
      "SLEEP": {
        "label": "Short Sleep Duration",
        "value": 33,
        "unit": "%",
        "year": "2022"
      },
      "CHECKUP": {
        "label": "Annual Checkup",
        "value": 74.4,
        "unit": "%",
        "year": "2023"
      },
      "CASTHMA": {
        "label": "Current Asthma",
        "value": 9.9,
        "unit": "%",
        "year": "2023"
      },
      "PHLTH": {
        "label": "Frequent Physical Distress",
        "value": 12.4,
        "unit": "%",
        "year": "2023"
      },
      "DIABETES": {
        "label": "Diabetes",
        "value": 11.4,
        "unit": "%",
        "year": "2023"
      },
      "OBESITY": {
        "label": "Obesity",
        "value": 42,
        "unit": "%",
        "year": "2023"
      },
      "DENTAL": {
        "label": "Dental Visit",
        "value": 67.2,
        "unit": "%",
        "year": "2022"
      },
      "MHLTH": {
        "label": "Frequent Mental Distress",
        "value": 15.3,
        "unit": "%",
        "year": "2023"
      },
      "ACCESS2": {
        "label": "Lack of Health Insurance",
        "value": 8.3,
        "unit": "%",
        "year": "2023"
      },
      "BPHIGH": {
        "label": "High Blood Pressure",
        "value": 33.5,
        "unit": "%",
        "year": "2023"
      },
      "STROKE": {
        "label": "Stroke",
        "value": 3.5,
        "unit": "%",
        "year": "2023"
      },
      "CHD": {
        "label": "Coronary Heart Disease",
        "value": 6.8,
        "unit": "%",
        "year": "2023"
      },
      "LPA": {
        "label": "Physical Inactivity",
        "value": 25.8,
        "unit": "%",
        "year": "2023"
      },
      "BINGE": {
        "label": "Binge Drinking",
        "value": 18.5,
        "unit": "%",
        "year": "2023"
      }
    },
    "totalPopulation": 36785,
    "source": "CDC PLACES (2023)"
  },
  "hospitals": null,
  "crime": {
    "year": 2022,
    "source": "state",
    "sourceLabel": "FBI Crime Data Explorer (UCR Summary)",
    "violentCrimeRate": 241,
    "propertyCrimeRate": 1980.8,
    "assaultRate": 180.5,
    "homicideRate": 3.2,
    "robberyRate": 57.3,
    "burglaryRate": 215.7,
    "larcenyRate": 1475.4,
    "motorVehicleTheftRate": 289.7
  },
  "history": {
    "years": [
      2013,
      2014,
      2015,
      2016,
      2017,
      2018,
      2019,
      2020,
      2021,
      2022,
      2023
    ],
    "population": [
      36321,
      36172,
      36046,
      35926,
      35816,
      35825,
      35832,
      35788,
      36662,
      36727,
      36771
    ],
    "medianIncome": [
      55170,
      56234,
      56128,
      57738,
      59869,
      61275,
      62121,
      62885,
      67067,
      73296,
      78468
    ],
    "povertyRate": [
      8.5,
      7.8,
      8.1,
      8.1,
      8.4,
      8.9,
      8.5,
      7.1,
      7.3,
      7.1,
      7.7
    ],
    "medianHomeValue": [
      155400,
      151400,
      148300,
      148400,
      150400,
      157900,
      164700,
      171200,
      184500,
      214300,
      233400
    ],
    "unemploymentRate": [
      6.1,
      5,
      4.5,
      3.8,
      3,
      2.6,
      2.9,
      2.7,
      3.3,
      3.2,
      3.3
    ]
  },
  "climate": {
    "station": "USC00213962",
    "stationName": "HUTCHINSON 1 N",
    "distanceMi": 1.5,
    "source": "NOAA Climate Normals 1991-2020",
    "monthly": {
      "jan": {
        "avgTemp": 13.4,
        "highTemp": 21.8,
        "lowTemp": 5,
        "precip": 0.6
      },
      "feb": {
        "avgTemp": 17.9,
        "highTemp": 26.5,
        "lowTemp": 9.3,
        "precip": 0.7
      },
      "mar": {
        "avgTemp": 31.8,
        "highTemp": 40.3,
        "lowTemp": 23.4,
        "precip": 1.3
      },
      "apr": {
        "avgTemp": 45.6,
        "highTemp": 55.8,
        "lowTemp": 35.5,
        "precip": 2.2
      },
      "may": {
        "avgTemp": 58.7,
        "highTemp": 69,
        "lowTemp": 48.4,
        "precip": 4
      },
      "jun": {
        "avgTemp": 68.8,
        "highTemp": 78.6,
        "lowTemp": 58.9,
        "precip": 4.5
      },
      "jul": {
        "avgTemp": 72.7,
        "highTemp": 82.7,
        "lowTemp": 62.6,
        "precip": 3.9
      },
      "aug": {
        "avgTemp": 70.2,
        "highTemp": 80.7,
        "lowTemp": 59.7,
        "precip": 4.8
      },
      "sep": {
        "avgTemp": 62.5,
        "highTemp": 73.6,
        "lowTemp": 51.5,
        "precip": 3
      },
      "oct": {
        "avgTemp": 48.3,
        "highTemp": 58.4,
        "lowTemp": 38.1,
        "precip": 2.5
      },
      "nov": {
        "avgTemp": 32.7,
        "highTemp": 40.5,
        "lowTemp": 24.8,
        "precip": 1.5
      },
      "dec": {
        "avgTemp": 19.7,
        "highTemp": 27.4,
        "lowTemp": 12,
        "precip": 0.9
      }
    },
    "annual": {
      "avgTemp": 45.2,
      "highTemp": 54.6,
      "lowTemp": 35.8,
      "totalPrecip": 29.9,
      "hotMonths": 2,
      "coldMonths": 5
    }
  }
}
